aws_credential_process.py
aws_credential_process-0.20.0.dist-info/entry_points.txt
aws_credential_process-0.20.0.dist-info/LICENSE.txt
aws_credential_process-0.20.0.dist-info/WHEEL
aws_credential_process-0.20.0.dist-info/METADATA
aws_credential_process-0.20.0.dist-info/RECORD
