Metadata-Version: 2.1
Name: aws-credential-process
Version: 0.20.0
Summary: AWS Credential Process
Home-page: https://github.com/meeuw/aws-credential-process
Keywords: AWS,MFA,keyring,keychain,yubikey
Author: Dick Marinus
Author-email: dick@mrns.nl
Requires-Python: >=3.7,<4.0
Classifier: Programming Language :: Python :: 3
Classifier: Programming Language :: Python :: 3.7
Classifier: Programming Language :: Python :: 3.8
Classifier: Programming Language :: Python :: 3.9
Classifier: Programming Language :: Python :: 3.10
Requires-Dist: boto3 (>=1,<2)
Requires-Dist: click (>=8.1,<9.0)
Requires-Dist: keyring (>=20.0.1)
Requires-Dist: pynentry (>=0.1,<0.2)
Requires-Dist: toml (>=0.10.2,<0.11.0)
Requires-Dist: yubikey-manager (==5.0.0)
Project-URL: Repository, https://github.com/meeuw/aws-credential-process
